printer/__init__.py
printer/printer.py
jason_personal_lib-0.1.2.dist-info/METADATA
jason_personal_lib-0.1.2.dist-info/WHEEL
jason_personal_lib-0.1.2.dist-info/top_level.txt
jason_personal_lib-0.1.2.dist-info/RECORD
