Metadata-Version: 2.4
Name: jason_personal_lib
Version: 0.1.2
Summary: jason's python lib
Requires-Python: >=3.6
Requires-Dist: wcwidth
